LICENSE
README.md
requirements.txt
setup.py
tachikoma/__init__.py
tachikoma/differs.py
tachikoma/pipeline.py
tachikoma/settings.py
tachikoma/util.py
tachikoma.egg-info/PKG-INFO
tachikoma.egg-info/SOURCES.txt
tachikoma.egg-info/dependency_links.txt
tachikoma.egg-info/requires.txt
tachikoma.egg-info/top_level.txt
tachikoma/analyzers/__init__.py
tachikoma/analyzers/aws.py
tachikoma/analyzers/slack.py
tachikoma/emitters/__init__.py
tachikoma/emitters/slack.py
tachikoma/generators/__init__.py
tachikoma/generators/slack.py
tachikoma/generators/aws/__init__.py
tachikoma/generators/aws/acm.py
tachikoma/generators/aws/iam.py
tachikoma/generators/aws/generator/__init__.py
tachikoma/generators/aws/generator/generate.py
tachikoma/persistance/__init__.py
tachikoma/persistance/shelve.py
tachikoma/tests/__init__.py
tachikoma/tests/test_end_to_end.py
tachikoma/tests/test_generators.py