Metadata-Version: 1.1
Name: tachikoma
Version: 1.5
Summary: Tachikoma is an alerting pipeline so smart it's scary
Home-page: https://github.com/CaliDog/tachikoma/
Author: Ryan Sears
Author-email: ryan@calidog.io
License: MIT
Platform: UNKNOWN
Classifier: Development Status :: 3 - Alpha
Classifier: License :: OSI Approved :: MIT License
Classifier: Topic :: Internet :: WWW/HTTP
Classifier: Operating System :: MacOS :: MacOS X
Classifier: Operating System :: POSIX
Classifier: Programming Language :: Python :: 3
Classifier: Framework :: AsyncIO
